{
  "schemaVersion": 1,
  "id": "stellarica",
  "version": "$version",
  "name": "Stellarica",
  "description": "I am very good at names!",
  "authors": [
    {
      "name": "trainb0y",
      "contact": {
        "email": "trainb0ydev@gmail.com",
        "discord": "trainb0y#7688"
      }
    }
  ],
  "contact": {
    "issues": "https://github.com/stellaricamc/stellarica/issues",
    "sources": "https://github.com/stellaricamc/stellarica"
  },
  "license": "MIT",
  "icon": "assets/stellarica/icon.png",
  "environment": "client",
  "entrypoints": {
    "client": [
      {
        "adapter": "kotlin",
        "value": "io.github.stellaricamc.stellarica.client.StellaricaClient"
      }
    ]
  },
  "depends": {
    "fabricloader": ">=0.14.10",
    "fabric-language-kotlin": ">=1.8.6+kotlin.1.7.21"
  },
  "recommends": {
    "modmenu": ">=5.0.0",
    "minecraft": ">=1.19.3"
  }
}
